Metadata-Version: 1.1
Name: django-humanize
Version: 0.1
Summary: Use humanize 3rd-party lib as template filters
Home-page: https://github.com/oasiswork/django-humanize/
Author: Jocelyn Delalande
Author-email: jdelalande@oasiswork.fr
License: BSD License
Platform: UNKNOWN
Classifier: Programming Language :: Python
Classifier: Programming Language :: Python :: 3
Classifier: Intended Audience :: Developers
Classifier: License :: OSI Approved :: MIT License
Classifier: Framework :: Django
